aind_mri_utils/__init__.py
aind_mri_utils/aliases.py
aind_mri_utils/arc_angles.py
aind_mri_utils/chemical_shift.py
aind_mri_utils/headframe_rotation.py
aind_mri_utils/implant.py
aind_mri_utils/measurement.py
aind_mri_utils/meshes.py
aind_mri_utils/optimization.py
aind_mri_utils/planning.py
aind_mri_utils/plots.py
aind_mri_utils/reticle_calibrations.py
aind_mri_utils/rotations.py
aind_mri_utils/sitk_volume.py
aind_mri_utils/utils.py
aind_mri_utils/file_io/__init__.py
aind_mri_utils/file_io/image_files.py
aind_mri_utils/file_io/obj_files.py
aind_mri_utils/file_io/simpleitk.py
aind_mri_utils-0.11.2.dist-info/licenses/LICENSE
aind_mri_utils-0.11.2.dist-info/METADATA
aind_mri_utils-0.11.2.dist-info/WHEEL
aind_mri_utils-0.11.2.dist-info/top_level.txt
aind_mri_utils-0.11.2.dist-info/RECORD
