Metadata-Version: 2.4
Name: aind_mri_utils
Version: 0.11.2
Summary: MRI utilities library for aind teams.
Author: Allen Institute for Neural Dynamics
Author-email: Galen Lynch <galen@galenlynch.com>, Yoni Browning <yoni.browning@alleninstitute.org>
License-Expression: MIT
Project-URL: Repository, https://github.com/AllenNeuralDynamics/aind-mri-utils/
Project-URL: Issues, https://github.com/AllenNeuralDynamics/aind-mri-utils/issues
Project-URL: Changelog, https://github.com/AllenNeuralDynamics/aind-mri-utils/blob/main/CHANGELOG.md
Classifier: Programming Language :: Python :: 3
Requires-Python: >=3.10
License-File: LICENSE
Requires-Dist: aind-anatomical-utils<0.5,>=0.1
Requires-Dist: matplotlib<4,>=3
Requires-Dist: numpy<3,>=1.7
Requires-Dist: openpyxl<4,>=3
Requires-Dist: pywavefront<2,>=1.3
Requires-Dist: Rtree<2,>=1
Requires-Dist: scipy<2,>=1
Requires-Dist: scikit-image<0.26,>=0.17
Requires-Dist: SimpleITK<3,>=2
Requires-Dist: trimesh<5,>=4
Dynamic: license-file
